discirc/__init__.py
discirc/discord_bot.py
discirc/irc_bot.py
discirc/launcher.py
discirc/message.py
discirc/signals.py
discirc-0.6.dist-info/LICENSE
discirc-0.6.dist-info/METADATA
discirc-0.6.dist-info/WHEEL
discirc-0.6.dist-info/entry_points.txt
discirc-0.6.dist-info/top_level.txt
discirc-0.6.dist-info/RECORD
