Metadata-Version: 2.1
Name: discirc
Version: 0.6
Summary: A Discord to IRC gateway
Home-page: http://pythonhosted.org/discirc/
Author: TROUVERIE Joachim
Author-email: joachim.trouverie@linoame.fr
License: UNKNOWN
Platform: UNKNOWN
Classifier: Development Status :: 4 - Beta
Classifier: Environment :: Console
Classifier: Topic :: Communications :: Chat
Classifier: License :: OSI Approved :: GNU General Public License v3 or later (GPLv3+)
Classifier: Natural Language :: English
Classifier: Programming Language :: Python :: 3.5
Requires-Dist: discord.py
Requires-Dist: bottom
Requires-Dist: requests
Requires-Dist: blinker
Requires-Dist: click
Requires-Dist: asyncblink
